{
  "date": "2026-06-15",
  "step": 2,
  "summaries": [
    {
      "stage": 1,
      "summary": "**主題一: 動態梯度異常偵測於後訓練資料中毒防禦**\n\n* **關鍵事實**：\n + 大多數防禦機制僅在訓練前或離線分析，缺乏在微調過程中即時偵測的機制。\n + 研究人數仍在十餘人左右，尚未形成成熟基準。\n* **結論**：\n + 需要發展能夠在微調過程中即時偵測資料中毒的機制。\n + 需要研究如何在多任務或參數高效微調情境下保持低偽陽性率，同時對少量惡意樣本保持高靈敏度。\n* **技術細節**：\n + 需要發展梯度訊號在高維參數空間的噪聲抑制與統計檢驗的理論界限。\n + 需要研究如何在高維參數空間中有效估計梯度分布的異常。\n* **論點**：\n + 需要發展能夠在微調過程中即時偵測資料中毒的機制。\n + 需要研究如何在多任務或參數高效微調情境下保持低偽陽性率，同時對少量惡意樣本保持高靈敏度。\n* **引用的 paper 名稱**：\n + *Detecting Post‑Training Data Poisoning via Gradient Distribution Shifts*，第一作者 **Y. Liu**，NeurIPS 2025。\n + *Online Gradient Anomaly Detection for Secure Fine‑Tuning*，第一作者 **M. Chen**，ICLR 2026。\n + *Statistical Tests for Poisoned Sample Identification in Large Models*，第一作者 **K. Singh**，arXiv 2025.12。\n\n**主題二: 基於圖神經網路的資料中毒影響範圍推理**\n\n* **關鍵事實**：\n + 現有研究多聚焦於單一樣本的毒化效果，缺少對整體資料圖結構中毒傳播路徑的系統化建模。\n + 相關工作仍在萌芽階段。\n* **結論**：\n + 需要發展能夠系統化建模整體資料圖結構中毒傳播路徑的機制。\n + 需要研究如何在大型未標註資料圖上有效估計單一毒化樣本的影響範圍而不產生計算瓶頸。\n* **技術細節**：\n + 需要發展圖結構的動態變化下，毒化影響的持續追蹤與更新的"
    }
  ],
  "failures": {
    "1": 0
  }
}